{
  "id": "2621779f-60a5-4705-ad37-4fd68bded992",
  "name": "Görev 24 — Potla Taban Kontrolü",
  "filename": "gorev_24_Potla_Taban_Kontrolu",
  "mode": "blocks",
  "blocksState": {
    "blocks": {
      "languageVersion": 0,
      "blocks": [
        {
          "type": "rx_on_start",
          "x": 40,
          "y": 40,
          "inputs": {
            "DO": {
              "block": {
                "type": "rx_pca9685_init",
                "fields": {
                  "SDA": 4,
                  "SCL": 5,
                  "ADDR": "40"
                }
              }
            }
          },
          "next": {
            "block": {
              "type": "rx_forever",
              "inputs": {
                "DO": {
                  "block": {
                    "type": "variables_set",
                    "fields": {
                      "VAR": {
                        "id": "var_deger",
                        "name": "deger",
                        "type": ""
                      }
                    },
                    "inputs": {
                      "VALUE": {
                        "block": {
                          "type": "rx_potentiometer",
                          "fields": {
                            "PIN": "26"
                          }
                        }
                      }
                    },
                    "next": {
                      "block": {
                        "type": "variables_set",
                        "fields": {
                          "VAR": {
                            "id": "var_aci",
                            "name": "aci",
                            "type": ""
                          }
                        },
                        "inputs": {
                          "VALUE": {
                            "block": {
                              "type": "rx_map",
                              "inputs": {
                                "VALUE": {
                                  "block": {
                                    "type": "variables_get",
                                    "fields": {
                                      "VAR": {
                                        "id": "var_deger",
                                        "name": "deger",
                                        "type": ""
                                      }
                                    }
                                  }
                                },
                                "FROM_LOW": {
                                  "block": {
                                    "type": "math_number",
                                    "fields": {
                                      "NUM": 0
                                    }
                                  }
                                },
                                "FROM_HIGH": {
                                  "block": {
                                    "type": "math_number",
                                    "fields": {
                                      "NUM": 100
                                    }
                                  }
                                },
                                "TO_LOW": {
                                  "block": {
                                    "type": "math_number",
                                    "fields": {
                                      "NUM": 30
                                    }
                                  }
                                },
                                "TO_HIGH": {
                                  "block": {
                                    "type": "math_number",
                                    "fields": {
                                      "NUM": 150
                                    }
                                  }
                                }
                              }
                            }
                          }
                        },
                        "next": {
                          "block": {
                            "type": "rx_servo_v3",
                            "fields": {
                              "CHANNEL": "0"
                            },
                            "inputs": {
                              "ANGLE": {
                                "block": {
                                  "type": "variables_get",
                                  "fields": {
                                    "VAR": {
                                      "id": "var_aci",
                                      "name": "aci",
                                      "type": ""
                                    }
                                  }
                                }
                              }
                            },
                            "next": {
                              "block": {
                                "type": "rx_delay_ms",
                                "inputs": {
                                  "MS": {
                                    "block": {
                                      "type": "math_number",
                                      "fields": {
                                        "NUM": 30
                                      }
                                    }
                                  }
                                }
                              }
                            }
                          }
                        }
                      }
                    }
                  }
                }
              }
            }
          }
        }
      ]
    },
    "variables": [
      {
        "name": "deger",
        "id": "var_deger"
      },
      {
        "name": "aci",
        "id": "var_aci"
      }
    ]
  },
  "code": null,
  "createdAt": 1783958492072,
  "updatedAt": 1783958492072
}