{
  "id": "15a4f7c8-148e-44c1-bb85-182f05cdeaa0",
  "name": "Görev 59 — Gece Bekçisi Robot",
  "filename": "gorev_59_Gece_Bekcisi_Robot",
  "mode": "blocks",
  "blocksState": {
    "blocks": {
      "languageVersion": 0,
      "blocks": [
        {
          "type": "procedures_defnoreturn",
          "fields": {
            "NAME": "renk_kirmizi"
          },
          "inputs": {
            "STACK": {
              "block": {
                "type": "rx_digital_write",
                "fields": {
                  "PIN": 9,
                  "STATE": "HIGH"
                },
                "next": {
                  "block": {
                    "type": "rx_digital_write",
                    "fields": {
                      "PIN": 10,
                      "STATE": "LOW"
                    },
                    "next": {
                      "block": {
                        "type": "rx_digital_write",
                        "fields": {
                          "PIN": 11,
                          "STATE": "LOW"
                        }
                      }
                    }
                  }
                }
              }
            }
          },
          "x": 820,
          "y": 40
        },
        {
          "type": "procedures_defnoreturn",
          "fields": {
            "NAME": "renk_mavi"
          },
          "inputs": {
            "STACK": {
              "block": {
                "type": "rx_digital_write",
                "fields": {
                  "PIN": 9,
                  "STATE": "LOW"
                },
                "next": {
                  "block": {
                    "type": "rx_digital_write",
                    "fields": {
                      "PIN": 10,
                      "STATE": "LOW"
                    },
                    "next": {
                      "block": {
                        "type": "rx_digital_write",
                        "fields": {
                          "PIN": 11,
                          "STATE": "HIGH"
                        }
                      }
                    }
                  }
                }
              }
            }
          },
          "x": 820,
          "y": 360
        },
        {
          "type": "procedures_defnoreturn",
          "fields": {
            "NAME": "renk_kapat"
          },
          "inputs": {
            "STACK": {
              "block": {
                "type": "rx_digital_write",
                "fields": {
                  "PIN": 9,
                  "STATE": "LOW"
                },
                "next": {
                  "block": {
                    "type": "rx_digital_write",
                    "fields": {
                      "PIN": 10,
                      "STATE": "LOW"
                    },
                    "next": {
                      "block": {
                        "type": "rx_digital_write",
                        "fields": {
                          "PIN": 11,
                          "STATE": "LOW"
                        }
                      }
                    }
                  }
                }
              }
            }
          },
          "x": 820,
          "y": 680
        },
        {
          "type": "rx_on_start",
          "x": 40,
          "y": 40,
          "inputs": {
            "DO": {
              "block": {
                "type": "rx_servo_angle",
                "fields": {
                  "PIN": 4
                },
                "inputs": {
                  "ANGLE": {
                    "block": {
                      "type": "math_number",
                      "fields": {
                        "NUM": 90
                      }
                    }
                  }
                },
                "next": {
                  "block": {
                    "type": "rx_servo_angle",
                    "fields": {
                      "PIN": 5
                    },
                    "inputs": {
                      "ANGLE": {
                        "block": {
                          "type": "math_number",
                          "fields": {
                            "NUM": 90
                          }
                        }
                      }
                    },
                    "next": {
                      "block": {
                        "type": "rx_servo_angle",
                        "fields": {
                          "PIN": 6
                        },
                        "inputs": {
                          "ANGLE": {
                            "block": {
                              "type": "math_number",
                              "fields": {
                                "NUM": 90
                              }
                            }
                          }
                        },
                        "next": {
                          "block": {
                            "type": "rx_servo_angle",
                            "fields": {
                              "PIN": 7
                            },
                            "inputs": {
                              "ANGLE": {
                                "block": {
                                  "type": "math_number",
                                  "fields": {
                                    "NUM": 90
                                  }
                                }
                              }
                            },
                            "next": {
                              "block": {
                                "type": "rx_forever",
                                "inputs": {
                                  "DO": {
                                    "block": {
                                      "type": "variables_set",
                                      "fields": {
                                        "VAR": {
                                          "id": "vid_isik",
                                          "name": "isik",
                                          "type": ""
                                        }
                                      },
                                      "inputs": {
                                        "VALUE": {
                                          "block": {
                                            "type": "rx_ldr_read",
                                            "fields": {
                                              "PIN": "27"
                                            }
                                          }
                                        }
                                      },
                                      "next": {
                                        "block": {
                                          "type": "controls_if",
                                          "inputs": {
                                            "IF0": {
                                              "block": {
                                                "type": "logic_compare",
                                                "fields": {
                                                  "OP": "LT"
                                                },
                                                "inputs": {
                                                  "A": {
                                                    "block": {
                                                      "type": "variables_get",
                                                      "fields": {
                                                        "VAR": {
                                                          "id": "vid_isik",
                                                          "name": "isik",
                                                          "type": ""
                                                        }
                                                      }
                                                    }
                                                  },
                                                  "B": {
                                                    "block": {
                                                      "type": "math_number",
                                                      "fields": {
                                                        "NUM": 20
                                                      }
                                                    }
                                                  }
                                                }
                                              }
                                            },
                                            "DO0": {
                                              "block": {
                                                "type": "variables_set",
                                                "fields": {
                                                  "VAR": {
                                                    "id": "vid_en_yakin",
                                                    "name": "en_yakin",
                                                    "type": ""
                                                  }
                                                },
                                                "inputs": {
                                                  "VALUE": {
                                                    "block": {
                                                      "type": "math_number",
                                                      "fields": {
                                                        "NUM": 999
                                                      }
                                                    }
                                                  }
                                                },
                                                "next": {
                                                  "block": {
                                                    "type": "variables_set",
                                                    "fields": {
                                                      "VAR": {
                                                        "id": "vid_hedef",
                                                        "name": "hedef",
                                                        "type": ""
                                                      }
                                                    },
                                                    "inputs": {
                                                      "VALUE": {
                                                        "block": {
                                                          "type": "math_number",
                                                          "fields": {
                                                            "NUM": 90
                                                          }
                                                        }
                                                      }
                                                    },
                                                    "next": {
                                                      "block": {
                                                        "type": "controls_for",
                                                        "fields": {
                                                          "VAR": {
                                                            "id": "vid_a",
                                                            "name": "a",
                                                            "type": ""
                                                          }
                                                        },
                                                        "inputs": {
                                                          "FROM": {
                                                            "block": {
                                                              "type": "math_number",
                                                              "fields": {
                                                                "NUM": 30
                                                              }
                                                            }
                                                          },
                                                          "TO": {
                                                            "block": {
                                                              "type": "math_number",
                                                              "fields": {
                                                                "NUM": 150
                                                              }
                                                            }
                                                          },
                                                          "BY": {
                                                            "block": {
                                                              "type": "math_number",
                                                              "fields": {
                                                                "NUM": 10
                                                              }
                                                            }
                                                          },
                                                          "DO": {
                                                            "block": {
                                                              "type": "rx_servo_angle",
                                                              "fields": {
                                                                "PIN": 4
                                                              },
                                                              "inputs": {
                                                                "ANGLE": {
                                                                  "block": {
                                                                    "type": "math_constrain",
                                                                    "inputs": {
                                                                      "VALUE": {
                                                                        "block": {
                                                                          "type": "variables_get",
                                                                          "fields": {
                                                                            "VAR": {
                                                                              "id": "vid_a",
                                                                              "name": "a",
                                                                              "type": ""
                                                                            }
                                                                          }
                                                                        }
                                                                      },
                                                                      "LOW": {
                                                                        "block": {
                                                                          "type": "math_number",
                                                                          "fields": {
                                                                            "NUM": 30
                                                                          }
                                                                        }
                                                                      },
                                                                      "HIGH": {
                                                                        "block": {
                                                                          "type": "math_number",
                                                                          "fields": {
                                                                            "NUM": 150
                                                                          }
                                                                        }
                                                                      }
                                                                    }
                                                                  }
                                                                }
                                                              },
                                                              "next": {
                                                                "block": {
                                                                  "type": "rx_delay_ms",
                                                                  "inputs": {
                                                                    "MS": {
                                                                      "block": {
                                                                        "type": "math_number",
                                                                        "fields": {
                                                                          "NUM": 150
                                                                        }
                                                                      }
                                                                    }
                                                                  },
                                                                  "next": {
                                                                    "block": {
                                                                      "type": "variables_set",
                                                                      "fields": {
                                                                        "VAR": {
                                                                          "id": "vid_m",
                                                                          "name": "m",
                                                                          "type": ""
                                                                        }
                                                                      },
                                                                      "inputs": {
                                                                        "VALUE": {
                                                                          "block": {
                                                                            "type": "rx_ultrasonic_distance",
                                                                            "fields": {
                                                                              "TRIG": 12,
                                                                              "ECHO": 13
                                                                            }
                                                                          }
                                                                        }
                                                                      },
                                                                      "next": {
                                                                        "block": {
                                                                          "type": "controls_if",
                                                                          "inputs": {
                                                                            "IF0": {
                                                                              "block": {
                                                                                "type": "logic_compare",
                                                                                "fields": {
                                                                                  "OP": "LT"
                                                                                },
                                                                                "inputs": {
                                                                                  "A": {
                                                                                    "block": {
                                                                                      "type": "variables_get",
                                                                                      "fields": {
                                                                                        "VAR": {
                                                                                          "id": "vid_m",
                                                                                          "name": "m",
                                                                                          "type": ""
                                                                                        }
                                                                                      }
                                                                                    }
                                                                                  },
                                                                                  "B": {
                                                                                    "block": {
                                                                                      "type": "variables_get",
                                                                                      "fields": {
                                                                                        "VAR": {
                                                                                          "id": "vid_en_yakin",
                                                                                          "name": "en_yakin",
                                                                                          "type": ""
                                                                                        }
                                                                                      }
                                                                                    }
                                                                                  }
                                                                                }
                                                                              }
                                                                            },
                                                                            "DO0": {
                                                                              "block": {
                                                                                "type": "variables_set",
                                                                                "fields": {
                                                                                  "VAR": {
                                                                                    "id": "vid_en_yakin",
                                                                                    "name": "en_yakin",
                                                                                    "type": ""
                                                                                  }
                                                                                },
                                                                                "inputs": {
                                                                                  "VALUE": {
                                                                                    "block": {
                                                                                      "type": "variables_get",
                                                                                      "fields": {
                                                                                        "VAR": {
                                                                                          "id": "vid_m",
                                                                                          "name": "m",
                                                                                          "type": ""
                                                                                        }
                                                                                      }
                                                                                    }
                                                                                  }
                                                                                },
                                                                                "next": {
                                                                                  "block": {
                                                                                    "type": "variables_set",
                                                                                    "fields": {
                                                                                      "VAR": {
                                                                                        "id": "vid_hedef",
                                                                                        "name": "hedef",
                                                                                        "type": ""
                                                                                      }
                                                                                    },
                                                                                    "inputs": {
                                                                                      "VALUE": {
                                                                                        "block": {
                                                                                          "type": "variables_get",
                                                                                          "fields": {
                                                                                            "VAR": {
                                                                                              "id": "vid_a",
                                                                                              "name": "a",
                                                                                              "type": ""
                                                                                            }
                                                                                          }
                                                                                        }
                                                                                      }
                                                                                    }
                                                                                  }
                                                                                }
                                                                              }
                                                                            }
                                                                          }
                                                                        }
                                                                      }
                                                                    }
                                                                  }
                                                                }
                                                              }
                                                            }
                                                          }
                                                        },
                                                        "next": {
                                                          "block": {
                                                            "type": "controls_if",
                                                            "inputs": {
                                                              "IF0": {
                                                                "block": {
                                                                  "type": "logic_compare",
                                                                  "fields": {
                                                                    "OP": "LT"
                                                                  },
                                                                  "inputs": {
                                                                    "A": {
                                                                      "block": {
                                                                        "type": "variables_get",
                                                                        "fields": {
                                                                          "VAR": {
                                                                            "id": "vid_en_yakin",
                                                                            "name": "en_yakin",
                                                                            "type": ""
                                                                          }
                                                                        }
                                                                      }
                                                                    },
                                                                    "B": {
                                                                      "block": {
                                                                        "type": "math_number",
                                                                        "fields": {
                                                                          "NUM": 15
                                                                        }
                                                                      }
                                                                    }
                                                                  }
                                                                }
                                                              },
                                                              "DO0": {
                                                                "block": {
                                                                  "type": "rx_print",
                                                                  "inputs": {
                                                                    "TEXT": {
                                                                      "block": {
                                                                        "type": "text_join",
                                                                        "extraState": {
                                                                          "itemCount": 2
                                                                        },
                                                                        "inputs": {
                                                                          "ADD0": {
                                                                            "block": {
                                                                              "type": "text",
                                                                              "fields": {
                                                                                "TEXT": "Hareket algilandi! Aci: "
                                                                              }
                                                                            }
                                                                          },
                                                                          "ADD1": {
                                                                            "block": {
                                                                              "type": "variables_get",
                                                                              "fields": {
                                                                                "VAR": {
                                                                                  "id": "vid_hedef",
                                                                                  "name": "hedef",
                                                                                  "type": ""
                                                                                }
                                                                              }
                                                                            }
                                                                          }
                                                                        }
                                                                      }
                                                                    }
                                                                  },
                                                                  "next": {
                                                                    "block": {
                                                                      "type": "rx_servo_angle",
                                                                      "fields": {
                                                                        "PIN": 4
                                                                      },
                                                                      "inputs": {
                                                                        "ANGLE": {
                                                                          "block": {
                                                                            "type": "math_constrain",
                                                                            "inputs": {
                                                                              "VALUE": {
                                                                                "block": {
                                                                                  "type": "variables_get",
                                                                                  "fields": {
                                                                                    "VAR": {
                                                                                      "id": "vid_hedef",
                                                                                      "name": "hedef",
                                                                                      "type": ""
                                                                                    }
                                                                                  }
                                                                                }
                                                                              },
                                                                              "LOW": {
                                                                                "block": {
                                                                                  "type": "math_number",
                                                                                  "fields": {
                                                                                    "NUM": 30
                                                                                  }
                                                                                }
                                                                              },
                                                                              "HIGH": {
                                                                                "block": {
                                                                                  "type": "math_number",
                                                                                  "fields": {
                                                                                    "NUM": 150
                                                                                  }
                                                                                }
                                                                              }
                                                                            }
                                                                          }
                                                                        }
                                                                      },
                                                                      "next": {
                                                                        "block": {
                                                                          "type": "controls_repeat_ext",
                                                                          "inputs": {
                                                                            "TIMES": {
                                                                              "block": {
                                                                                "type": "math_number",
                                                                                "fields": {
                                                                                  "NUM": 5
                                                                                }
                                                                              }
                                                                            },
                                                                            "DO": {
                                                                              "block": {
                                                                                "type": "procedures_callnoreturn",
                                                                                "extraState": {
                                                                                  "name": "renk_kirmizi"
                                                                                },
                                                                                "inputs": {},
                                                                                "next": {
                                                                                  "block": {
                                                                                    "type": "rx_buzzer_tone",
                                                                                    "fields": {
                                                                                      "PIN": 8
                                                                                    },
                                                                                    "inputs": {
                                                                                      "FREQ": {
                                                                                        "block": {
                                                                                          "type": "math_number",
                                                                                          "fields": {
                                                                                            "NUM": 2000
                                                                                          }
                                                                                        }
                                                                                      },
                                                                                      "DUR": {
                                                                                        "block": {
                                                                                          "type": "math_number",
                                                                                          "fields": {
                                                                                            "NUM": 150
                                                                                          }
                                                                                        }
                                                                                      }
                                                                                    },
                                                                                    "next": {
                                                                                      "block": {
                                                                                        "type": "rx_delay_ms",
                                                                                        "inputs": {
                                                                                          "MS": {
                                                                                            "block": {
                                                                                              "type": "math_number",
                                                                                              "fields": {
                                                                                                "NUM": 80
                                                                                              }
                                                                                            }
                                                                                          }
                                                                                        },
                                                                                        "next": {
                                                                                          "block": {
                                                                                            "type": "procedures_callnoreturn",
                                                                                            "extraState": {
                                                                                              "name": "renk_kapat"
                                                                                            },
                                                                                            "inputs": {},
                                                                                            "next": {
                                                                                              "block": {
                                                                                                "type": "rx_delay_ms",
                                                                                                "inputs": {
                                                                                                  "MS": {
                                                                                                    "block": {
                                                                                                      "type": "math_number",
                                                                                                      "fields": {
                                                                                                        "NUM": 120
                                                                                                      }
                                                                                                    }
                                                                                                  }
                                                                                                }
                                                                                              }
                                                                                            }
                                                                                          }
                                                                                        }
                                                                                      }
                                                                                    }
                                                                                  }
                                                                                }
                                                                              }
                                                                            }
                                                                          }
                                                                        }
                                                                      }
                                                                    }
                                                                  }
                                                                }
                                                              }
                                                            }
                                                          }
                                                        }
                                                      }
                                                    }
                                                  }
                                                }
                                              }
                                            },
                                            "ELSE": {
                                              "block": {
                                                "type": "procedures_callnoreturn",
                                                "extraState": {
                                                  "name": "renk_mavi"
                                                },
                                                "inputs": {},
                                                "next": {
                                                  "block": {
                                                    "type": "rx_servo_angle",
                                                    "fields": {
                                                      "PIN": 4
                                                    },
                                                    "inputs": {
                                                      "ANGLE": {
                                                        "block": {
                                                          "type": "math_number",
                                                          "fields": {
                                                            "NUM": 90
                                                          }
                                                        }
                                                      }
                                                    },
                                                    "next": {
                                                      "block": {
                                                        "type": "rx_servo_angle",
                                                        "fields": {
                                                          "PIN": 5
                                                        },
                                                        "inputs": {
                                                          "ANGLE": {
                                                            "block": {
                                                              "type": "math_number",
                                                              "fields": {
                                                                "NUM": 90
                                                              }
                                                            }
                                                          }
                                                        },
                                                        "next": {
                                                          "block": {
                                                            "type": "rx_servo_angle",
                                                            "fields": {
                                                              "PIN": 6
                                                            },
                                                            "inputs": {
                                                              "ANGLE": {
                                                                "block": {
                                                                  "type": "math_number",
                                                                  "fields": {
                                                                    "NUM": 90
                                                                  }
                                                                }
                                                              }
                                                            },
                                                            "next": {
                                                              "block": {
                                                                "type": "rx_servo_angle",
                                                                "fields": {
                                                                  "PIN": 7
                                                                },
                                                                "inputs": {
                                                                  "ANGLE": {
                                                                    "block": {
                                                                      "type": "math_number",
                                                                      "fields": {
                                                                        "NUM": 90
                                                                      }
                                                                    }
                                                                  }
                                                                },
                                                                "next": {
                                                                  "block": {
                                                                    "type": "rx_delay_s",
                                                                    "inputs": {
                                                                      "S": {
                                                                        "block": {
                                                                          "type": "math_number",
                                                                          "fields": {
                                                                            "NUM": 1
                                                                          }
                                                                        }
                                                                      }
                                                                    }
                                                                  }
                                                                }
                                                              }
                                                            }
                                                          }
                                                        }
                                                      }
                                                    }
                                                  }
                                                }
                                              }
                                            }
                                          },
                                          "extraState": {
                                            "elseCount": 1
                                          },
                                          "next": {
                                            "block": {
                                              "type": "rx_delay_ms",
                                              "inputs": {
                                                "MS": {
                                                  "block": {
                                                    "type": "math_number",
                                                    "fields": {
                                                      "NUM": 200
                                                    }
                                                  }
                                                }
                                              }
                                            }
                                          }
                                        }
                                      }
                                    }
                                  }
                                }
                              }
                            }
                          }
                        }
                      }
                    }
                  }
                }
              }
            }
          }
        }
      ]
    },
    "variables": [
      {
        "name": "isik",
        "id": "vid_isik"
      },
      {
        "name": "en_yakin",
        "id": "vid_en_yakin"
      },
      {
        "name": "hedef",
        "id": "vid_hedef"
      },
      {
        "name": "a",
        "id": "vid_a"
      },
      {
        "name": "m",
        "id": "vid_m"
      }
    ]
  },
  "code": null,
  "createdAt": 1783960917244,
  "updatedAt": 1783960917244
}